import_deps/__init__.py
import_deps/__main__.py
import_deps/core.py
import_deps/graph.py
import_deps-0.5.1.dist-info/METADATA
import_deps-0.5.1.dist-info/WHEEL
import_deps-0.5.1.dist-info/entry_points.txt
import_deps-0.5.1.dist-info/licenses/LICENSE
import_deps-0.5.1.dist-info/RECORD
