Metadata-Version: 2.4
Name: import_deps
Version: 0.5.1
Summary: find python module imports
Project-URL: Homepage, https://github.com/schettino72/import-deps
Project-URL: Repository, https://github.com/schettino72/import-deps
Project-URL: Issues, https://github.com/schettino72/import-deps/issues
Author-email: Eduardo Naufel Schettino <schettino72@gmail.com>
License: MIT
License-File: LICENSE
Keywords: graph,import,quality
Classifier: Development Status :: 5 - Production/Stable
Classifier: Environment :: Console
Classifier: Intended Audience :: Developers
Classifier: License :: OSI Approved :: MIT License
Classifier: Natural Language :: English
Classifier: Operating System :: OS Independent
Classifier: Operating System :: POSIX
Classifier: Programming Language :: Python :: 3
Classifier: Programming Language :: Python :: 3.10
Classifier: Programming Language :: Python :: 3.11
Classifier: Programming Language :: Python :: 3.12
Classifier: Programming Language :: Python :: 3.13
Classifier: Programming Language :: Python :: 3.14
Classifier: Topic :: Software Development :: Quality Assurance
Requires-Python: >=3.10
Provides-Extra: dev
Requires-Dist: coverage; extra == 'dev'
Requires-Dist: doit; extra == 'dev'
Requires-Dist: doit-py; extra == 'dev'
Requires-Dist: pyflakes; extra == 'dev'
Requires-Dist: pytest; extra == 'dev'
Requires-Dist: pytest-cov; extra == 'dev'
